setup.py
hicplotlib/GenomicIntervals.py
hicplotlib/HiCParameters.py
hicplotlib/HiCPlot.py
hicplotlib/__init__.py
hicplotlib.egg-info/PKG-INFO
hicplotlib.egg-info/SOURCES.txt
hicplotlib.egg-info/dependency_links.txt
hicplotlib.egg-info/requires.txt
hicplotlib.egg-info/top_level.txt