Metadata-Version: 1.0
Name: hicplotlib
Version: 0.2.1
Summary: Hi-C data plotting and analysis tool
Home-page: https://github.com/Phlya/hicplotlib
Author: Ilya Flyamer
Author-email: flyamer@gmail.com
License: UNKNOWN
Platform: UNKNOWN
